gocept.month-3.0-py3.7-nspkg.pth
gocept/month/__init__.py
gocept/month/_month.py
gocept/month/adapter.py
gocept/month/configure.zcml
gocept/month/field.py
gocept/month/interfaces.py
gocept/month/interval.py
gocept/month/browser/__init__.py
gocept/month/browser/configure.zcml
gocept/month/browser/month_input.pt
gocept/month/browser/widget.py
gocept/month/tests/__init__.py
gocept/month/tests/test_month.py
gocept.month-3.0.dist-info/LICENSE.txt
gocept.month-3.0.dist-info/METADATA
gocept.month-3.0.dist-info/WHEEL
gocept.month-3.0.dist-info/namespace_packages.txt
gocept.month-3.0.dist-info/top_level.txt
gocept.month-3.0.dist-info/RECORD
