Metadata-Version: 2.1
Name: gocept.month
Version: 3.0
Summary: A datatype which stores a year and a month.
Home-page: https://github.com/gocept/gocept.month
Author: gocept gmbh & co. kg
Author-email: mail@gocept.com
License: MIT
Project-URL: Issue Tracker, https://github.com/gocept/gocept.month/issues
Project-URL: Sources, https://github.com/gocept/gocept.month
Project-URL: Changelog, https://raw.githubusercontent.com/gocept/gocept.month/main/CHANGES.rst
Platform: UNKNOWN
Classifier: License :: OSI Approved
Classifier: License :: OSI Approved :: MIT License
Classifier: Programming Language :: Python
Classifier: Programming Language :: Python :: 3
Classifier: Programming Language :: Python :: 3 :: Only
Classifier: Programming Language :: Python :: 3.6
Classifier: Programming Language :: Python :: 3.7
Classifier: Programming Language :: Python :: 3.8
Classifier: Programming Language :: Python :: 3.9
Classifier: Programming Language :: Python :: 3.10
Classifier: Programming Language :: Python :: Implementation :: CPython
Classifier: Programming Language :: Python :: Implementation :: PyPy
Classifier: Development Status :: 5 - Production/Stable
Classifier: Framework :: Zope :: 3
Classifier: Framework :: Zope :: 4
Classifier: Framework :: Zope :: 5
Classifier: Framework :: Pyramid
Classifier: Framework :: Plone
Classifier: Intended Audience :: Developers
Classifier: Natural Language :: English
Classifier: Operating System :: OS Independent
Classifier: Topic :: Software Development
Classifier: Topic :: Software Development :: Libraries
Classifier: Topic :: Software Development :: Libraries :: Python Modules
Classifier: Topic :: Utilities
Requires-Python: >=3.7
Requires-Dist: setuptools
Requires-Dist: zope.component
Requires-Dist: zope.i18nmessageid
Requires-Dist: zope.interface (>=4.0)
Requires-Dist: zope.schema
Provides-Extra: form
Requires-Dist: z3c.form (>=3.0) ; extra == 'form'
Requires-Dist: zope.formlib (>=4.0) ; extra == 'form'
Provides-Extra: test
Requires-Dist: plone.testing (>=5.1) ; extra == 'test'
